PhrExt/__init__.py
PhrExt/configuration.py
PhrExt/dataloader.py
PhrExt/label_converter.py
PhrExt/model.py
PhrExt/pl_wrapper.py
PhrExt/postprocess.py
PhrExt-0.1.0.dist-info/METADATA
PhrExt-0.1.0.dist-info/WHEEL
PhrExt-0.1.0.dist-info/top_level.txt
PhrExt-0.1.0.dist-info/RECORD
