Metadata-Version: 2.1
Name: PhrExt
Version: 0.1.0
Summary: Extract phrase from English sentence such as noun, verb, preposition based on NLP task word chunking and HuggingFace library
Author: Le Minh Khoi
License: MIT
Classifier: Programming Language :: Python :: 3
Classifier: License :: OSI Approved :: MIT License
Classifier: Operating System :: OS Independent
Requires-Python: >=3.8
